{
  "scenario_id": "elektronik_kemahalan_09",
  "bidang": "elektronik",
  "produk": "smartphone mid-range",
  "persona": {
    "tipe": "skeptis",
    "emosi_awal": "ragu"
  },
  "grounding": {
    "framework": [
      "SPIN",
      "AIDA",
      "FAB",
      "objection-handling"
    ],
    "generator": "grounded-local-v2",
    "divalidasi_manusia": false
  },
  "turns": [
    {
      "speaker": "sales",
      "text": "Selamat siang, Pak, terima kasih sudah mampir. Ada model tertentu yang sudah diincar atau mau saya bantu carikan?",
      "teknik": "sapa_rapport",
      "kualitas": "baik"
    },
    {
      "speaker": "pelanggan",
      "text": "Lagi butuh smartphone mid-range nih, buat anak sekolah untuk belajar online.",
      "keberatan": null,
      "emosi": "ragu"
    },
    {
      "speaker": "sales",
      "text": "Supaya rekomendasinya tepat, boleh saya tahu apa yang bikin Bapak/Ibu tertarik ke smartphone mid-range ini?",
      "teknik": "gali_kebutuhan",
      "kualitas": "baik"
    },
    {
      "speaker": "pelanggan",
      "text": "Nah itu yang saya mau tahu.",
      "keberatan": null,
      "emosi": "netral"
    },
    {
      "speaker": "sales",
      "text": "Keunggulan utamanya yang relevan buat Bapak/Ibu begini: RAM-nya besar dan chipset-nya kencang, dijamin lancar 3-4 tahun ke depan.",
      "teknik": "presentasi_manfaat",
      "kualitas": "baik"
    },
    {
      "speaker": "pelanggan",
      "text": "Ada yang lebih murah nggak? Ini di luar budget.",
      "keberatan": "harga",
      "emosi": "ragu"
    },
    {
      "speaker": "sales",
      "text": "Saya mengerti maksud Bapak/Ibu. Izinkan saya luruskan: saya carikan yang sesuai kantong dulu, yang penting kebutuhan utamanya tetap terpenuhi.",
      "teknik": "atasi_keberatan",
      "kualitas": "baik"
    },
    {
      "speaker": "pelanggan",
      "text": "Hmm, tapi beneran ya?",
      "keberatan": null,
      "emosi": "tertarik"
    },
    {
      "speaker": "sales",
      "text": "Biar pas, Bapak/Ibu lebih nyaman ambil yang ini atau yang tadi satunya? Saya siapkan yang dipilih.",
      "teknik": "closing",
      "kualitas": "baik"
    },
    {
      "speaker": "pelanggan",
      "text": "Boleh, kita lanjut.",
      "keberatan": null,
      "emosi": "tertarik"
    },
    {
      "speaker": "sales",
      "text": "Supaya lebih tenang pemakaiannya, earbuds nirkabel dengan harga bundling bisa saya bundling dengan harga lebih baik. Mau?",
      "teknik": "upsell",
      "kualitas": "baik"
    }
  ]
}