{
  "scenario_id": "otomotif_bandingkan_merk_01",
  "bidang": "otomotif",
  "produk": "LCGC 1.000cc",
  "persona": {
    "tipe": "sensitif_harga",
    "emosi_awal": "hati_hati"
  },
  "grounding": {
    "framework": [
      "SPIN",
      "AIDA",
      "FAB",
      "objection-handling"
    ],
    "generator": "grounded-local-v2",
    "divalidasi_manusia": false
  },
  "turns": [
    {
      "speaker": "sales",
      "text": "Halo Mbak, apa kabar? Silakan, kalau ada yang menarik nanti saya jelaskan detailnya ya.",
      "teknik": "sapa_rapport",
      "kualitas": "baik"
    },
    {
      "speaker": "pelanggan",
      "text": "Kebetulan lagi cari LCGC 1.000cc nih. Yang sebelah spesifikasinya kelihatan mirip tapi lebih murah.",
      "keberatan": "bandingkan_kompetitor",
      "emosi": "hati_hati"
    },
    {
      "speaker": "sales",
      "text": "Sebelum saya sarankan, boleh saya tanya kebutuhannya dulu? Ini lebih ke harian ke kantor, atau ada prioritas lain?",
      "teknik": "gali_kebutuhan",
      "kualitas": "baik"
    },
    {
      "speaker": "pelanggan",
      "text": "Iya, betul.",
      "keberatan": null,
      "emosi": "netral"
    },
    {
      "speaker": "sales",
      "text": "Coba saya jelaskan yang paling nyambung dengan kebutuhan tadi: meski kecil, kabinnya sudah muat 5 orang dengan AC yang dingin merata.",
      "teknik": "presentasi_manfaat",
      "kualitas": "baik"
    },
    {
      "speaker": "pelanggan",
      "text": "Hmm boleh juga.",
      "keberatan": null,
      "emosi": "netral"
    },
    {
      "speaker": "sales",
      "text": "Masa tidak percaya sama saya? Ini barang bagus lho.",
      "teknik": "atasi_keberatan",
      "kualitas": "lemah"
    },
    {
      "speaker": "pelanggan",
      "text": "Hmm boleh juga.",
      "keberatan": null,
      "emosi": "tertarik"
    },
    {
      "speaker": "pelanggan",
      "text": "Tapi tetap agak mahal ya.",
      "keberatan": "harga",
      "emosi": "ragu"
    },
    {
      "speaker": "sales",
      "text": "Yaudah Mbak saya kasih diskon deh biar sama kayak yang lain.",
      "teknik": "atasi_keberatan",
      "kualitas": "lemah"
    },
    {
      "speaker": "pelanggan",
      "text": "Ya sudah kalau begitu.",
      "keberatan": null,
      "emosi": "netral"
    },
    {
      "speaker": "sales",
      "text": "Gimana kalau kita lanjut ke simulasi cicilan sekarang? Biar Bapak/Ibu makin mantap.",
      "teknik": "closing",
      "kualitas": "baik"
    },
    {
      "speaker": "pelanggan",
      "text": "Yaudah kalau cicilannya masuk, saya jadi.",
      "keberatan": null,
      "emosi": "tertarik"
    }
  ]
}